sanic_mongodb_ext/__init__.py
sanic_mongodb_extension-0.6.0.dist-info/LICENSE
sanic_mongodb_extension-0.6.0.dist-info/METADATA
sanic_mongodb_extension-0.6.0.dist-info/WHEEL
sanic_mongodb_extension-0.6.0.dist-info/top_level.txt
sanic_mongodb_extension-0.6.0.dist-info/RECORD
