Metadata-Version: 2.1
Name: sanic-mongodb-extension
Version: 0.6.0
Summary: MongoDB with μMongo ODM support for Sanic framework
Home-page: https://github.com/Relrin/sanic-mongodb-extension
Author: Valeryi Savich
Author-email: relrin78@gmail.com
License: BSD
Platform: any
Classifier: Environment :: Web Environment
Classifier: License :: OSI Approved :: BSD License
Classifier: Intended Audience :: Developers
Classifier: Programming Language :: Python
Classifier: Programming Language :: Python :: 3
Classifier: Programming Language :: Python :: 3.5
Classifier: Programming Language :: Python :: 3.6
Classifier: Programming Language :: Python :: 3.7
Classifier: Topic :: Software Development :: Libraries :: Python Modules
License-File: LICENSE
Requires-Dist: sanic-base-extension (==0.2.0)
Requires-Dist: motor (==3.1.2)
Requires-Dist: umongo (==3.1.0)
